pdm_plugin_i-0.2.1.dist-info/METADATA
pdm_plugin_i-0.2.1.dist-info/WHEEL
pdm_plugin_i-0.2.1.dist-info/entry_points.txt
pdm_plugin_i-0.2.1.dist-info/licenses/LICENSE
pdm_plugin_i/__init__.py
pdm_plugin_i/command.py
pdm_plugin_i/py.typed
pdm_plugin_i-0.2.1.dist-info/RECORD
