Metadata-Version: 2.1
Name: pdm-plugin-i
Version: 0.2.1
Summary: A PDM plugin that make `pdm i` as alias of `pdm install`
Author-Email: Waket Zheng <waketzheng@gmail.com>
License: MIT
Classifier: Development Status :: 3 - Alpha
Classifier: Intended Audience :: Developers
Classifier: Environment :: Plugins
Classifier: Typing :: Typed
Classifier: Programming Language :: Python :: 3
Classifier: Programming Language :: Python :: 3.9
Classifier: Programming Language :: Python :: 3.10
Classifier: Programming Language :: Python :: 3.11
Classifier: Programming Language :: Python :: 3.12
Classifier: Programming Language :: Python :: 3.13
Project-URL: Repository, https://github.com/waketzheng/pdm-plugin-i
Project-URL: Homepage, https://github.com/waketzheng/pdm-plugin-i
Requires-Python: >=3.9
